PyAeroAcoustics/PyAeroAcoustics.py
PyAeroAcoustics/__init__.py
PyAeroAcoustics/Spectrum/Spectrum.py
PyAeroAcoustics/Spectrum/__init__.py
PyAeroAcoustics-0.0.5.dist-info/METADATA
PyAeroAcoustics-0.0.5.dist-info/WHEEL
PyAeroAcoustics-0.0.5.dist-info/top_level.txt
PyAeroAcoustics-0.0.5.dist-info/RECORD
