Metadata-Version: 2.1
Name: PyAeroAcoustics
Version: 0.0.5
Summary: PyAeroAcoustics
Home-page: UNKNOWN
Author: Thomas Brunner
Author-email: <thomas.brunner@tugraz.at>
License: UNKNOWN
Keywords: python,PyAeroAcoustics
Platform: UNKNOWN
Classifier: Development Status :: 3 - Alpha
Classifier: Intended Audience :: Education
Classifier: Programming Language :: Python :: 2
Classifier: Programming Language :: Python :: 3
Classifier: Operating System :: MacOS :: MacOS X
Classifier: Operating System :: Microsoft :: Windows
